dcinside_scraper/__init__.py
dcinside_scraper/scraper.py
dcinside_scraper-0.1.0.dist-info/METADATA
dcinside_scraper-0.1.0.dist-info/WHEEL
dcinside_scraper-0.1.0.dist-info/entry_points.txt
dcinside_scraper-0.1.0.dist-info/top_level.txt
dcinside_scraper-0.1.0.dist-info/RECORD
