Metadata-Version: 2.1
Name: dcinside_scraper
Version: 0.1.0
Summary: A package to scrape posts from DCInside
Home-page: https://github.com/yourusername/dcinside_scraper
Author: Your Name
Author-email: your.email@example.com
Classifier: Programming Language :: Python :: 3
Classifier: License :: OSI Approved :: MIT License
Classifier: Operating System :: OS Independent
Requires-Python: >=3.6
Requires-Dist: requests
Requires-Dist: beautifulsoup4
Requires-Dist: pandas
